{
  "task_1": [
    {
      "clusterization_id": 1,
      "fitness_score": 106.9927425977722,
      "is_valid": true,
      "clusters": [
        {
          "cluster_id": 1,
          "warehouse_id": 1,
          "transport_type": "car",
          "order_ids": [
            1,
            31,
            30,
            37,
            41
          ]
        },
        {
          "cluster_id": 2,
          "warehouse_id": 1,
          "transport_type": "car",
          "order_ids": [
            2,
            44,
            6,
            8,
            10
          ]
        },
        {
          "cluster_id": 3,
          "warehouse_id": 1,
          "transport_type": "car",
          "order_ids": [
            3,
            28,
            43
          ]
        },
        {
          "cluster_id": 4,
          "warehouse_id": 1,
          "transport_type": "car",
          "order_ids": [
            4,
            7,
            20,
            26,
            19
          ]
        },
        {
          "cluster_id": 5,
          "warehouse_id": 1,
          "transport_type": "car",
          "order_ids": [
            5,
            22,
            25
          ]
        },
        {
          "cluster_id": 6,
          "warehouse_id": 1,
          "transport_type": "car",
          "order_ids": [
            9,
            35,
            16,
            40,
            33
          ]
        },
        {
          "cluster_id": 7,
          "warehouse_id": 1,
          "transport_type": "car",
          "order_ids": [
            29,
            11,
            34,
            48,
            27
          ]
        },
        {
          "cluster_id": 8,
          "warehouse_id": 1,
          "transport_type": "car",
          "order_ids": [
            12,
            13,
            14,
            23,
            15
          ]
        },
        {
          "cluster_id": 9,
          "warehouse_id": 1,
          "transport_type": "car",
          "order_ids": [
            17
          ]
        },
        {
          "cluster_id": 10,
          "warehouse_id": 1,
          "transport_type": "car",
          "order_ids": [
            46,
            18,
            21,
            50,
            24
          ]
        },
        {
          "cluster_id": 11,
          "warehouse_id": 1,
          "transport_type": "car",
          "order_ids": [
            32,
            42,
            45,
            49
          ]
        },
        {
          "cluster_id": 12,
          "warehouse_id": 1,
          "transport_type": "car",
          "order_ids": [
            36
          ]
        },
        {
          "cluster_id": 13,
          "warehouse_id": 1,
          "transport_type": "car",
          "order_ids": [
            39,
            38,
            47
          ]
        },
        {
          "cluster_id": 14,
          "warehouse_id": 2,
          "transport_type": "car",
          "order_ids": [
            65,
            51,
            91,
            60,
            97
          ]
        },
        {
          "cluster_id": 15,
          "warehouse_id": 2,
          "transport_type": "car",
          "order_ids": [
            63,
            52,
            81,
            89,
            72
          ]
        },
        {
          "cluster_id": 16,
          "warehouse_id": 2,
          "transport_type": "car",
          "order_ids": [
            53,
            75,
            66
          ]
        },
        {
          "cluster_id": 17,
          "warehouse_id": 2,
          "transport_type": "car",
          "order_ids": [
            54,
            90,
            99,
            100,
            58
          ]
        },
        {
          "cluster_id": 18,
          "warehouse_id": 2,
          "transport_type": "car",
          "order_ids": [
            55,
            64,
            82,
            87,
            88
          ]
        },
        {
          "cluster_id": 19,
          "warehouse_id": 2,
          "transport_type": "car",
          "order_ids": [
            80,
            56,
            74,
            85,
            79
          ]
        },
        {
          "cluster_id": 20,
          "warehouse_id": 2,
          "transport_type": "car",
          "order_ids": [
            61,
            57,
            70,
            78,
            96
          ]
        },
        {
          "cluster_id": 21,
          "warehouse_id": 2,
          "transport_type": "car",
          "order_ids": [
            59,
            69,
            83,
            94,
            71
          ]
        },
        {
          "cluster_id": 22,
          "warehouse_id": 2,
          "transport_type": "car",
          "order_ids": [
            77,
            62,
            68,
            98,
            93
          ]
        },
        {
          "cluster_id": 23,
          "warehouse_id": 2,
          "transport_type": "car",
          "order_ids": [
            84,
            67,
            92,
            95,
            76
          ]
        },
        {
          "cluster_id": 24,
          "warehouse_id": 2,
          "transport_type": "car",
          "order_ids": [
            73,
            86
          ]
        }
      ]
    }
  ],
  "task_2": [
    {
      "clusterization_id": 1,
      "fitness_score": 216.3859423111852,
      "is_valid": false,
      "clusters": [
        {
          "cluster_id": 1,
          "warehouse_id": 1,
          "transport_type": "car",
          "order_ids": [
            1,
            18,
            47,
            49,
            33
          ]
        },
        {
          "cluster_id": 2,
          "warehouse_id": 1,
          "transport_type": "car",
          "order_ids": [
            2,
            11,
            21,
            27,
            41
          ]
        },
        {
          "cluster_id": 3,
          "warehouse_id": 1,
          "transport_type": "car",
          "order_ids": [
            3,
            4,
            26,
            45,
            42
          ]
        },
        {
          "cluster_id": 4,
          "warehouse_id": 1,
          "transport_type": "car",
          "order_ids": [
            5,
            28,
            34,
            19,
            7
          ]
        },
        {
          "cluster_id": 5,
          "warehouse_id": 1,
          "transport_type": "car",
          "order_ids": [
            14,
            38,
            6,
            16,
            43
          ]
        },
        {
          "cluster_id": 6,
          "warehouse_id": 1,
          "transport_type": "car",
          "order_ids": [
            8,
            30,
            39,
            13
          ]
        },
        {
          "cluster_id": 7,
          "warehouse_id": 1,
          "transport_type": "car",
          "order_ids": [
            9,
            32,
            50,
            12,
            20
          ]
        },
        {
          "cluster_id": 8,
          "warehouse_id": 1,
          "transport_type": "car",
          "order_ids": [
            31,
            24,
            35,
            10,
            48
          ]
        },
        {
          "cluster_id": 9,
          "warehouse_id": 1,
          "transport_type": "car",
          "order_ids": [
            15,
            25,
            36,
            46,
            23
          ]
        },
        {
          "cluster_id": 10,
          "warehouse_id": 1,
          "transport_type": "car",
          "order_ids": [
            22,
            17,
            44,
            29,
            37
          ]
        },
        {
          "cluster_id": 11,
          "warehouse_id": 1,
          "transport_type": "car",
          "order_ids": [
            40
          ]
        },
        {
          "cluster_id": 12,
          "warehouse_id": 2,
          "transport_type": "car",
          "order_ids": [
            51,
            83,
            52
          ]
        },
        {
          "cluster_id": 13,
          "warehouse_id": 2,
          "transport_type": "car",
          "order_ids": [
            53,
            72
          ]
        },
        {
          "cluster_id": 14,
          "warehouse_id": 2,
          "transport_type": "car",
          "order_ids": [
            54,
            67,
            81,
            68,
            82
          ]
        },
        {
          "cluster_id": 15,
          "warehouse_id": 2,
          "transport_type": "car",
          "order_ids": [
            55,
            56,
            71,
            91,
            89
          ]
        },
        {
          "cluster_id": 16,
          "warehouse_id": 2,
          "transport_type": "car",
          "order_ids": [
            65,
            57,
            78
          ]
        },
        {
          "cluster_id": 17,
          "warehouse_id": 2,
          "transport_type": "car",
          "order_ids": [
            80,
            58,
            87,
            97,
            99
          ]
        },
        {
          "cluster_id": 18,
          "warehouse_id": 2,
          "transport_type": "car",
          "order_ids": [
            59,
            77,
            85,
            95
          ]
        },
        {
          "cluster_id": 19,
          "warehouse_id": 2,
          "transport_type": "car",
          "order_ids": [
            60,
            73,
            61,
            88,
            76
          ]
        },
        {
          "cluster_id": 20,
          "warehouse_id": 2,
          "transport_type": "car",
          "order_ids": [
            62,
            64,
            96,
            69,
            98
          ]
        },
        {
          "cluster_id": 21,
          "warehouse_id": 2,
          "transport_type": "car",
          "order_ids": [
            70,
            63,
            90,
            100,
            92
          ]
        },
        {
          "cluster_id": 22,
          "warehouse_id": 2,
          "transport_type": "car",
          "order_ids": [
            66,
            74,
            94
          ]
        },
        {
          "cluster_id": 23,
          "warehouse_id": 2,
          "transport_type": "car",
          "order_ids": [
            75,
            79,
            84,
            93,
            86
          ]
        },
        {
          "cluster_id": 24,
          "warehouse_id": 3,
          "transport_type": "car",
          "order_ids": [
            108,
            101,
            118,
            150,
            120
          ]
        },
        {
          "cluster_id": 25,
          "warehouse_id": 3,
          "transport_type": "car",
          "order_ids": [
            110,
            102,
            111,
            134,
            123
          ]
        },
        {
          "cluster_id": 26,
          "warehouse_id": 3,
          "transport_type": "car",
          "order_ids": [
            103,
            129,
            148,
            143,
            106
          ]
        },
        {
          "cluster_id": 27,
          "warehouse_id": 3,
          "transport_type": "car",
          "order_ids": [
            104,
            138,
            141
          ]
        },
        {
          "cluster_id": 28,
          "warehouse_id": 3,
          "transport_type": "car",
          "order_ids": [
            105,
            115,
            147,
            121
          ]
        },
        {
          "cluster_id": 29,
          "warehouse_id": 3,
          "transport_type": "car",
          "order_ids": [
            107,
            149,
            117,
            119,
            131
          ]
        },
        {
          "cluster_id": 30,
          "warehouse_id": 3,
          "transport_type": "car",
          "order_ids": [
            135,
            109,
            133,
            140,
            137
          ]
        },
        {
          "cluster_id": 31,
          "warehouse_id": 3,
          "transport_type": "car",
          "order_ids": [
            122,
            112,
            132,
            144
          ]
        },
        {
          "cluster_id": 32,
          "warehouse_id": 3,
          "transport_type": "car",
          "order_ids": [
            113,
            127,
            145
          ]
        },
        {
          "cluster_id": 33,
          "warehouse_id": 3,
          "transport_type": "car",
          "order_ids": [
            114,
            130,
            136,
            124
          ]
        },
        {
          "cluster_id": 34,
          "warehouse_id": 3,
          "transport_type": "car",
          "order_ids": [
            126,
            116,
            128,
            146
          ]
        },
        {
          "cluster_id": 35,
          "warehouse_id": 3,
          "transport_type": "car",
          "order_ids": [
            125,
            139,
            142
          ]
        }
      ]
    }
  ],
  "task_3": [
    {
      "clusterization_id": 1,
      "fitness_score": 2035.0562112269736,
      "is_valid": false,
      "clusters": [
        {
          "cluster_id": 1,
          "warehouse_id": 1,
          "transport_type": "car",
          "order_ids": [
            1,
            37,
            48,
            21
          ]
        },
        {
          "cluster_id": 2,
          "warehouse_id": 1,
          "transport_type": "car",
          "order_ids": [
            25,
            2,
            42,
            50
          ]
        },
        {
          "cluster_id": 3,
          "warehouse_id": 1,
          "transport_type": "car",
          "order_ids": [
            3,
            20,
            17,
            9,
            44
          ]
        },
        {
          "cluster_id": 4,
          "warehouse_id": 1,
          "transport_type": "car",
          "order_ids": [
            4,
            5,
            10,
            30,
            33
          ]
        },
        {
          "cluster_id": 5,
          "warehouse_id": 1,
          "transport_type": "car",
          "order_ids": [
            6,
            12,
            23,
            36,
            28
          ]
        },
        {
          "cluster_id": 6,
          "warehouse_id": 1,
          "transport_type": "car",
          "order_ids": [
            7
          ]
        },
        {
          "cluster_id": 7,
          "warehouse_id": 1,
          "transport_type": "car",
          "order_ids": [
            35,
            8,
            46,
            32,
            41
          ]
        },
        {
          "cluster_id": 8,
          "warehouse_id": 1,
          "transport_type": "car",
          "order_ids": [
            11,
            13,
            29,
            34,
            49
          ]
        },
        {
          "cluster_id": 9,
          "warehouse_id": 1,
          "transport_type": "car",
          "order_ids": [
            14,
            16,
            22,
            24,
            40
          ]
        },
        {
          "cluster_id": 10,
          "warehouse_id": 1,
          "transport_type": "car",
          "order_ids": [
            15,
            31,
            38,
            45,
            47
          ]
        },
        {
          "cluster_id": 11,
          "warehouse_id": 1,
          "transport_type": "car",
          "order_ids": [
            18,
            39
          ]
        },
        {
          "cluster_id": 12,
          "warehouse_id": 1,
          "transport_type": "car",
          "order_ids": [
            19,
            26,
            27,
            43
          ]
        },
        {
          "cluster_id": 13,
          "warehouse_id": 2,
          "transport_type": "car",
          "order_ids": [
            62,
            51,
            60,
            96
          ]
        },
        {
          "cluster_id": 14,
          "warehouse_id": 2,
          "transport_type": "car",
          "order_ids": [
            52,
            54,
            56,
            97,
            84
          ]
        },
        {
          "cluster_id": 15,
          "warehouse_id": 2,
          "transport_type": "car",
          "order_ids": [
            53,
            87,
            67,
            81,
            95
          ]
        },
        {
          "cluster_id": 16,
          "warehouse_id": 2,
          "transport_type": "car",
          "order_ids": [
            55,
            72,
            71,
            80,
            74
          ]
        },
        {
          "cluster_id": 17,
          "warehouse_id": 2,
          "transport_type": "car",
          "order_ids": [
            57
          ]
        },
        {
          "cluster_id": 18,
          "warehouse_id": 2,
          "transport_type": "car",
          "order_ids": [
            58,
            76,
            77,
            70,
            93
          ]
        },
        {
          "cluster_id": 19,
          "warehouse_id": 2,
          "transport_type": "car",
          "order_ids": [
            59,
            68,
            69,
            98,
            82
          ]
        },
        {
          "cluster_id": 20,
          "warehouse_id": 2,
          "transport_type": "car",
          "order_ids": [
            61,
            65,
            86,
            75,
            91
          ]
        },
        {
          "cluster_id": 21,
          "warehouse_id": 2,
          "transport_type": "car",
          "order_ids": [
            99,
            83,
            63,
            100,
            92
          ]
        },
        {
          "cluster_id": 22,
          "warehouse_id": 2,
          "transport_type": "car",
          "order_ids": [
            64,
            66,
            78,
            73,
            90
          ]
        },
        {
          "cluster_id": 23,
          "warehouse_id": 2,
          "transport_type": "car",
          "order_ids": [
            88,
            79,
            94,
            89,
            85
          ]
        },
        {
          "cluster_id": 24,
          "warehouse_id": 3,
          "transport_type": "car",
          "order_ids": [
            102,
            101,
            103,
            123,
            111
          ]
        },
        {
          "cluster_id": 25,
          "warehouse_id": 3,
          "transport_type": "car",
          "order_ids": [
            104,
            118
          ]
        },
        {
          "cluster_id": 26,
          "warehouse_id": 3,
          "transport_type": "car",
          "order_ids": [
            133,
            105,
            130,
            115,
            146
          ]
        },
        {
          "cluster_id": 27,
          "warehouse_id": 3,
          "transport_type": "car",
          "order_ids": [
            121,
            113,
            125,
            106,
            138
          ]
        },
        {
          "cluster_id": 28,
          "warehouse_id": 3,
          "transport_type": "car",
          "order_ids": [
            107
          ]
        },
        {
          "cluster_id": 29,
          "warehouse_id": 3,
          "transport_type": "car",
          "order_ids": [
            108,
            126
          ]
        },
        {
          "cluster_id": 30,
          "warehouse_id": 3,
          "transport_type": "car",
          "order_ids": [
            109,
            116,
            127,
            128,
            132
          ]
        },
        {
          "cluster_id": 31,
          "warehouse_id": 3,
          "transport_type": "car",
          "order_ids": [
            114,
            131,
            110,
            140,
            143
          ]
        },
        {
          "cluster_id": 32,
          "warehouse_id": 3,
          "transport_type": "car",
          "order_ids": [
            112,
            139
          ]
        },
        {
          "cluster_id": 33,
          "warehouse_id": 3,
          "transport_type": "car",
          "order_ids": [
            134,
            117,
            141,
            147,
            149
          ]
        },
        {
          "cluster_id": 34,
          "warehouse_id": 3,
          "transport_type": "car",
          "order_ids": [
            119,
            135,
            142,
            145,
            150
          ]
        },
        {
          "cluster_id": 35,
          "warehouse_id": 3,
          "transport_type": "car",
          "order_ids": [
            129,
            120,
            137
          ]
        },
        {
          "cluster_id": 36,
          "warehouse_id": 3,
          "transport_type": "car",
          "order_ids": [
            122,
            136,
            124,
            148
          ]
        },
        {
          "cluster_id": 37,
          "warehouse_id": 3,
          "transport_type": "car",
          "order_ids": [
            144
          ]
        },
        {
          "cluster_id": 38,
          "warehouse_id": 4,
          "transport_type": "car",
          "order_ids": [
            152,
            166,
            151,
            195,
            194
          ]
        },
        {
          "cluster_id": 39,
          "warehouse_id": 4,
          "transport_type": "car",
          "order_ids": [
            153,
            154,
            157,
            176,
            165
          ]
        },
        {
          "cluster_id": 40,
          "warehouse_id": 4,
          "transport_type": "car",
          "order_ids": [
            155,
            178,
            199,
            187,
            200
          ]
        },
        {
          "cluster_id": 41,
          "warehouse_id": 4,
          "transport_type": "car",
          "order_ids": [
            156,
            162,
            175,
            174,
            197
          ]
        },
        {
          "cluster_id": 42,
          "warehouse_id": 4,
          "transport_type": "car",
          "order_ids": [
            168,
            158,
            198,
            163,
            188
          ]
        },
        {
          "cluster_id": 43,
          "warehouse_id": 4,
          "transport_type": "car",
          "order_ids": [
            170,
            159,
            180,
            169,
            183
          ]
        },
        {
          "cluster_id": 44,
          "warehouse_id": 4,
          "transport_type": "car",
          "order_ids": [
            177,
            160,
            161,
            190,
            193
          ]
        },
        {
          "cluster_id": 45,
          "warehouse_id": 4,
          "transport_type": "car",
          "order_ids": [
            164,
            179,
            189
          ]
        },
        {
          "cluster_id": 46,
          "warehouse_id": 4,
          "transport_type": "car",
          "order_ids": [
            182,
            185,
            167,
            191
          ]
        },
        {
          "cluster_id": 47,
          "warehouse_id": 4,
          "transport_type": "car",
          "order_ids": [
            172,
            181,
            186,
            171,
            196
          ]
        },
        {
          "cluster_id": 48,
          "warehouse_id": 4,
          "transport_type": "car",
          "order_ids": [
            173
          ]
        },
        {
          "cluster_id": 49,
          "warehouse_id": 4,
          "transport_type": "car",
          "order_ids": [
            184,
            192
          ]
        }
      ]
    }
  ],
  "task_4": [
    {
      "clusterization_id": 1,
      "fitness_score": 690.3312677886134,
      "is_valid": false,
      "clusters": [
        {
          "cluster_id": 1,
          "warehouse_id": 1,
          "transport_type": "car",
          "order_ids": [
            20,
            1,
            17,
            43,
            39
          ]
        },
        {
          "cluster_id": 2,
          "warehouse_id": 1,
          "transport_type": "car",
          "order_ids": [
            23,
            2,
            16,
            44,
            38
          ]
        },
        {
          "cluster_id": 3,
          "warehouse_id": 1,
          "transport_type": "car",
          "order_ids": [
            8,
            3,
            46,
            6,
            10
          ]
        },
        {
          "cluster_id": 4,
          "warehouse_id": 1,
          "transport_type": "car",
          "order_ids": [
            4,
            7,
            12,
            18,
            37
          ]
        },
        {
          "cluster_id": 5,
          "warehouse_id": 1,
          "transport_type": "car",
          "order_ids": [
            5,
            49,
            48
          ]
        },
        {
          "cluster_id": 6,
          "warehouse_id": 1,
          "transport_type": "car",
          "order_ids": [
            9,
            31,
            33,
            24,
            35
          ]
        },
        {
          "cluster_id": 7,
          "warehouse_id": 1,
          "transport_type": "car",
          "order_ids": [
            11,
            22,
            29,
            26,
            42
          ]
        },
        {
          "cluster_id": 8,
          "warehouse_id": 1,
          "transport_type": "car",
          "order_ids": [
            13,
            21,
            45,
            32,
            50
          ]
        },
        {
          "cluster_id": 9,
          "warehouse_id": 1,
          "transport_type": "car",
          "order_ids": [
            19,
            14,
            41
          ]
        },
        {
          "cluster_id": 10,
          "warehouse_id": 1,
          "transport_type": "car",
          "order_ids": [
            25,
            28,
            15,
            40,
            34
          ]
        },
        {
          "cluster_id": 11,
          "warehouse_id": 1,
          "transport_type": "car",
          "order_ids": [
            36,
            27,
            47,
            30
          ]
        },
        {
          "cluster_id": 12,
          "warehouse_id": 2,
          "transport_type": "car",
          "order_ids": [
            51,
            53,
            61,
            97,
            100
          ]
        },
        {
          "cluster_id": 13,
          "warehouse_id": 2,
          "transport_type": "car",
          "order_ids": [
            52,
            62,
            63,
            67,
            95
          ]
        },
        {
          "cluster_id": 14,
          "warehouse_id": 2,
          "transport_type": "car",
          "order_ids": [
            54,
            69,
            74,
            98,
            75
          ]
        },
        {
          "cluster_id": 15,
          "warehouse_id": 2,
          "transport_type": "car",
          "order_ids": [
            55,
            70,
            77,
            83,
            91
          ]
        },
        {
          "cluster_id": 16,
          "warehouse_id": 2,
          "transport_type": "car",
          "order_ids": [
            56,
            66,
            82,
            86,
            88
          ]
        },
        {
          "cluster_id": 17,
          "warehouse_id": 2,
          "transport_type": "car",
          "order_ids": [
            57,
            71,
            60,
            80,
            96
          ]
        },
        {
          "cluster_id": 18,
          "warehouse_id": 2,
          "transport_type": "car",
          "order_ids": [
            58,
            81,
            90,
            99
          ]
        },
        {
          "cluster_id": 19,
          "warehouse_id": 2,
          "transport_type": "car",
          "order_ids": [
            59,
            68,
            85,
            92,
            84
          ]
        },
        {
          "cluster_id": 20,
          "warehouse_id": 2,
          "transport_type": "car",
          "order_ids": [
            64,
            65,
            72,
            79
          ]
        },
        {
          "cluster_id": 21,
          "warehouse_id": 2,
          "transport_type": "car",
          "order_ids": [
            73,
            76,
            87,
            93,
            89
          ]
        },
        {
          "cluster_id": 22,
          "warehouse_id": 2,
          "transport_type": "car",
          "order_ids": [
            78,
            94
          ]
        },
        {
          "cluster_id": 23,
          "warehouse_id": 3,
          "transport_type": "car",
          "order_ids": [
            108,
            125,
            101,
            103,
            144
          ]
        },
        {
          "cluster_id": 24,
          "warehouse_id": 3,
          "transport_type": "car",
          "order_ids": [
            104,
            102,
            109,
            140,
            150
          ]
        },
        {
          "cluster_id": 25,
          "warehouse_id": 3,
          "transport_type": "car",
          "order_ids": [
            119,
            105,
            134,
            123,
            132
          ]
        },
        {
          "cluster_id": 26,
          "warehouse_id": 3,
          "transport_type": "car",
          "order_ids": [
            106,
            107,
            112,
            128,
            143
          ]
        },
        {
          "cluster_id": 27,
          "warehouse_id": 3,
          "transport_type": "car",
          "order_ids": [
            110,
            124,
            129,
            142,
            145
          ]
        },
        {
          "cluster_id": 28,
          "warehouse_id": 3,
          "transport_type": "car",
          "order_ids": [
            111,
            127,
            135,
            146,
            149
          ]
        },
        {
          "cluster_id": 29,
          "warehouse_id": 3,
          "transport_type": "car",
          "order_ids": [
            130,
            113,
            120,
            131,
            116
          ]
        },
        {
          "cluster_id": 30,
          "warehouse_id": 3,
          "transport_type": "car",
          "order_ids": [
            114,
            122,
            121,
            133,
            126
          ]
        },
        {
          "cluster_id": 31,
          "warehouse_id": 3,
          "transport_type": "car",
          "order_ids": [
            136,
            115,
            137,
            118,
            147
          ]
        },
        {
          "cluster_id": 32,
          "warehouse_id": 3,
          "transport_type": "car",
          "order_ids": [
            138,
            139,
            117,
            141,
            148
          ]
        },
        {
          "cluster_id": 33,
          "warehouse_id": 4,
          "transport_type": "car",
          "order_ids": [
            165,
            151,
            178
          ]
        },
        {
          "cluster_id": 34,
          "warehouse_id": 4,
          "transport_type": "car",
          "order_ids": [
            164,
            152,
            181
          ]
        },
        {
          "cluster_id": 35,
          "warehouse_id": 4,
          "transport_type": "car",
          "order_ids": [
            153,
            157,
            170,
            183,
            173
          ]
        },
        {
          "cluster_id": 36,
          "warehouse_id": 4,
          "transport_type": "car",
          "order_ids": [
            154,
            158,
            168,
            194,
            197
          ]
        },
        {
          "cluster_id": 37,
          "warehouse_id": 4,
          "transport_type": "car",
          "order_ids": [
            156,
            155,
            193,
            199,
            166
          ]
        },
        {
          "cluster_id": 38,
          "warehouse_id": 4,
          "transport_type": "car",
          "order_ids": [
            159,
            180,
            188,
            177,
            182
          ]
        },
        {
          "cluster_id": 39,
          "warehouse_id": 4,
          "transport_type": "car",
          "order_ids": [
            160,
            161
          ]
        },
        {
          "cluster_id": 40,
          "warehouse_id": 4,
          "transport_type": "car",
          "order_ids": [
            169,
            162,
            187,
            191,
            174
          ]
        },
        {
          "cluster_id": 41,
          "warehouse_id": 4,
          "transport_type": "car",
          "order_ids": [
            179,
            163,
            186,
            167,
            190
          ]
        },
        {
          "cluster_id": 42,
          "warehouse_id": 4,
          "transport_type": "car",
          "order_ids": [
            171,
            175,
            172,
            195
          ]
        },
        {
          "cluster_id": 43,
          "warehouse_id": 4,
          "transport_type": "car",
          "order_ids": [
            176,
            192,
            198,
            189
          ]
        },
        {
          "cluster_id": 44,
          "warehouse_id": 4,
          "transport_type": "car",
          "order_ids": [
            184,
            185,
            196
          ]
        },
        {
          "cluster_id": 45,
          "warehouse_id": 4,
          "transport_type": "car",
          "order_ids": [
            200
          ]
        },
        {
          "cluster_id": 46,
          "warehouse_id": 5,
          "transport_type": "car",
          "order_ids": [
            221,
            201,
            206,
            215,
            250
          ]
        },
        {
          "cluster_id": 47,
          "warehouse_id": 5,
          "transport_type": "car",
          "order_ids": [
            202,
            210,
            223,
            209,
            227
          ]
        },
        {
          "cluster_id": 48,
          "warehouse_id": 5,
          "transport_type": "car",
          "order_ids": [
            203,
            222,
            214,
            245,
            207
          ]
        },
        {
          "cluster_id": 49,
          "warehouse_id": 5,
          "transport_type": "car",
          "order_ids": [
            204,
            229,
            242
          ]
        },
        {
          "cluster_id": 50,
          "warehouse_id": 5,
          "transport_type": "car",
          "order_ids": [
            208,
            205,
            237,
            247
          ]
        },
        {
          "cluster_id": 51,
          "warehouse_id": 5,
          "transport_type": "car",
          "order_ids": [
            217,
            220,
            211,
            212,
            230
          ]
        },
        {
          "cluster_id": 52,
          "warehouse_id": 5,
          "transport_type": "car",
          "order_ids": [
            213,
            232,
            238,
            249,
            236
          ]
        },
        {
          "cluster_id": 53,
          "warehouse_id": 5,
          "transport_type": "car",
          "order_ids": [
            216,
            239,
            224,
            226,
            243
          ]
        },
        {
          "cluster_id": 54,
          "warehouse_id": 5,
          "transport_type": "car",
          "order_ids": [
            231,
            218,
            241,
            248,
            233
          ]
        },
        {
          "cluster_id": 55,
          "warehouse_id": 5,
          "transport_type": "car",
          "order_ids": [
            219,
            240,
            244,
            246
          ]
        },
        {
          "cluster_id": 56,
          "warehouse_id": 5,
          "transport_type": "car",
          "order_ids": [
            225,
            234
          ]
        },
        {
          "cluster_id": 57,
          "warehouse_id": 5,
          "transport_type": "car",
          "order_ids": [
            228,
            235
          ]
        }
      ]
    }
  ],
  "task_5": [
    {
      "clusterization_id": 1,
      "fitness_score": 146.87370738875234,
      "is_valid": true,
      "clusters": [
        {
          "cluster_id": 1,
          "warehouse_id": 1,
          "transport_type": "car",
          "order_ids": [
            13,
            1,
            29,
            33,
            49
          ]
        },
        {
          "cluster_id": 2,
          "warehouse_id": 1,
          "transport_type": "car",
          "order_ids": [
            2,
            28,
            40,
            22,
            30
          ]
        },
        {
          "cluster_id": 3,
          "warehouse_id": 1,
          "transport_type": "car",
          "order_ids": [
            3,
            14,
            5,
            17,
            19
          ]
        },
        {
          "cluster_id": 4,
          "warehouse_id": 1,
          "transport_type": "car",
          "order_ids": [
            4,
            24,
            27,
            31
          ]
        },
        {
          "cluster_id": 5,
          "warehouse_id": 1,
          "transport_type": "car",
          "order_ids": [
            6,
            21,
            23,
            36,
            44
          ]
        },
        {
          "cluster_id": 6,
          "warehouse_id": 1,
          "transport_type": "car",
          "order_ids": [
            7,
            12,
            10,
            47,
            42
          ]
        },
        {
          "cluster_id": 7,
          "warehouse_id": 1,
          "transport_type": "car",
          "order_ids": [
            8,
            9,
            15
          ]
        },
        {
          "cluster_id": 8,
          "warehouse_id": 1,
          "transport_type": "car",
          "order_ids": [
            11,
            39,
            50,
            32,
            46
          ]
        },
        {
          "cluster_id": 9,
          "warehouse_id": 1,
          "transport_type": "car",
          "order_ids": [
            16,
            34
          ]
        },
        {
          "cluster_id": 10,
          "warehouse_id": 1,
          "transport_type": "car",
          "order_ids": [
            37,
            18,
            35,
            43
          ]
        },
        {
          "cluster_id": 11,
          "warehouse_id": 1,
          "transport_type": "car",
          "order_ids": [
            20,
            25,
            41,
            45,
            48
          ]
        },
        {
          "cluster_id": 12,
          "warehouse_id": 1,
          "transport_type": "car",
          "order_ids": [
            26,
            38
          ]
        },
        {
          "cluster_id": 13,
          "warehouse_id": 2,
          "transport_type": "car",
          "order_ids": [
            51,
            58,
            64,
            90,
            77
          ]
        },
        {
          "cluster_id": 14,
          "warehouse_id": 2,
          "transport_type": "car",
          "order_ids": [
            52,
            62,
            79,
            83
          ]
        },
        {
          "cluster_id": 15,
          "warehouse_id": 2,
          "transport_type": "car",
          "order_ids": [
            80,
            53,
            68,
            94,
            56
          ]
        },
        {
          "cluster_id": 16,
          "warehouse_id": 2,
          "transport_type": "car",
          "order_ids": [
            67,
            54,
            70,
            87,
            72
          ]
        },
        {
          "cluster_id": 17,
          "warehouse_id": 2,
          "transport_type": "car",
          "order_ids": [
            55,
            65,
            86,
            82,
            91
          ]
        },
        {
          "cluster_id": 18,
          "warehouse_id": 2,
          "transport_type": "car",
          "order_ids": [
            57,
            75,
            71,
            78,
            95
          ]
        },
        {
          "cluster_id": 19,
          "warehouse_id": 2,
          "transport_type": "car",
          "order_ids": [
            76,
            84,
            59,
            92,
            100
          ]
        },
        {
          "cluster_id": 20,
          "warehouse_id": 2,
          "transport_type": "car",
          "order_ids": [
            60,
            73,
            96,
            97
          ]
        },
        {
          "cluster_id": 21,
          "warehouse_id": 2,
          "transport_type": "car",
          "order_ids": [
            61,
            63
          ]
        },
        {
          "cluster_id": 22,
          "warehouse_id": 2,
          "transport_type": "car",
          "order_ids": [
            74,
            81,
            66,
            89,
            98
          ]
        },
        {
          "cluster_id": 23,
          "warehouse_id": 2,
          "transport_type": "car",
          "order_ids": [
            69,
            88,
            85,
            93,
            99
          ]
        },
        {
          "cluster_id": 24,
          "warehouse_id": 3,
          "transport_type": "car",
          "order_ids": [
            101,
            119,
            130,
            118,
            148
          ]
        },
        {
          "cluster_id": 25,
          "warehouse_id": 3,
          "transport_type": "car",
          "order_ids": [
            102,
            116,
            142,
            146
          ]
        },
        {
          "cluster_id": 26,
          "warehouse_id": 3,
          "transport_type": "car",
          "order_ids": [
            124,
            103,
            117,
            150,
            135
          ]
        },
        {
          "cluster_id": 27,
          "warehouse_id": 3,
          "transport_type": "car",
          "order_ids": [
            104,
            108,
            109,
            121,
            110
          ]
        },
        {
          "cluster_id": 28,
          "warehouse_id": 3,
          "transport_type": "car",
          "order_ids": [
            105,
            145
          ]
        },
        {
          "cluster_id": 29,
          "warehouse_id": 3,
          "transport_type": "car",
          "order_ids": [
            113,
            106,
            112,
            120,
            123
          ]
        },
        {
          "cluster_id": 30,
          "warehouse_id": 3,
          "transport_type": "car",
          "order_ids": [
            107,
            111,
            128,
            132,
            134
          ]
        },
        {
          "cluster_id": 31,
          "warehouse_id": 3,
          "transport_type": "car",
          "order_ids": [
            129,
            114,
            138,
            139,
            144
          ]
        },
        {
          "cluster_id": 32,
          "warehouse_id": 3,
          "transport_type": "car",
          "order_ids": [
            122,
            115,
            149,
            131,
            143
          ]
        },
        {
          "cluster_id": 33,
          "warehouse_id": 3,
          "transport_type": "car",
          "order_ids": [
            125,
            127,
            136,
            141,
            147
          ]
        },
        {
          "cluster_id": 34,
          "warehouse_id": 3,
          "transport_type": "car",
          "order_ids": [
            126,
            137,
            140
          ]
        },
        {
          "cluster_id": 35,
          "warehouse_id": 3,
          "transport_type": "car",
          "order_ids": [
            133
          ]
        }
      ]
    }
  ],
  "task_6": [
    {
      "clusterization_id": 1,
      "fitness_score": 635.0168525059016,
      "is_valid": false,
      "clusters": [
        {
          "cluster_id": 1,
          "warehouse_id": 1,
          "transport_type": "car",
          "order_ids": [
            1,
            26,
            32,
            35,
            50
          ]
        },
        {
          "cluster_id": 2,
          "warehouse_id": 1,
          "transport_type": "car",
          "order_ids": [
            2,
            16,
            20,
            40,
            28
          ]
        },
        {
          "cluster_id": 3,
          "warehouse_id": 1,
          "transport_type": "car",
          "order_ids": [
            3,
            5,
            6,
            39,
            31
          ]
        },
        {
          "cluster_id": 4,
          "warehouse_id": 1,
          "transport_type": "car",
          "order_ids": [
            17,
            4,
            24,
            23,
            46
          ]
        },
        {
          "cluster_id": 5,
          "warehouse_id": 1,
          "transport_type": "car",
          "order_ids": [
            7,
            14
          ]
        },
        {
          "cluster_id": 6,
          "warehouse_id": 1,
          "transport_type": "car",
          "order_ids": [
            13,
            8,
            15,
            19,
            29
          ]
        },
        {
          "cluster_id": 7,
          "warehouse_id": 1,
          "transport_type": "car",
          "order_ids": [
            9,
            33
          ]
        },
        {
          "cluster_id": 8,
          "warehouse_id": 1,
          "transport_type": "car",
          "order_ids": [
            10,
            27,
            37,
            49,
            38
          ]
        },
        {
          "cluster_id": 9,
          "warehouse_id": 1,
          "transport_type": "car",
          "order_ids": [
            11,
            22,
            48,
            44,
            45
          ]
        },
        {
          "cluster_id": 10,
          "warehouse_id": 1,
          "transport_type": "car",
          "order_ids": [
            12,
            21,
            25
          ]
        },
        {
          "cluster_id": 11,
          "warehouse_id": 1,
          "transport_type": "car",
          "order_ids": [
            18,
            41,
            30
          ]
        },
        {
          "cluster_id": 12,
          "warehouse_id": 1,
          "transport_type": "car",
          "order_ids": [
            34,
            43,
            47,
            42,
            36
          ]
        },
        {
          "cluster_id": 13,
          "warehouse_id": 2,
          "transport_type": "car",
          "order_ids": [
            51,
            67,
            62,
            78,
            94
          ]
        },
        {
          "cluster_id": 14,
          "warehouse_id": 2,
          "transport_type": "car",
          "order_ids": [
            52,
            80,
            83,
            57,
            81
          ]
        },
        {
          "cluster_id": 15,
          "warehouse_id": 2,
          "transport_type": "car",
          "order_ids": [
            64,
            72,
            53,
            79,
            89
          ]
        },
        {
          "cluster_id": 16,
          "warehouse_id": 2,
          "transport_type": "car",
          "order_ids": [
            54,
            58
          ]
        },
        {
          "cluster_id": 17,
          "warehouse_id": 2,
          "transport_type": "car",
          "order_ids": [
            55,
            84
          ]
        },
        {
          "cluster_id": 18,
          "warehouse_id": 2,
          "transport_type": "car",
          "order_ids": [
            56,
            76,
            63,
            93,
            100
          ]
        },
        {
          "cluster_id": 19,
          "warehouse_id": 2,
          "transport_type": "car",
          "order_ids": [
            59,
            69,
            74,
            86,
            91
          ]
        },
        {
          "cluster_id": 20,
          "warehouse_id": 2,
          "transport_type": "car",
          "order_ids": [
            61,
            60,
            88,
            90
          ]
        },
        {
          "cluster_id": 21,
          "warehouse_id": 2,
          "transport_type": "car",
          "order_ids": [
            82,
            65,
            85,
            99,
            92
          ]
        },
        {
          "cluster_id": 22,
          "warehouse_id": 2,
          "transport_type": "car",
          "order_ids": [
            66,
            77,
            97,
            87,
            96
          ]
        },
        {
          "cluster_id": 23,
          "warehouse_id": 2,
          "transport_type": "car",
          "order_ids": [
            68,
            70,
            73,
            75,
            98
          ]
        },
        {
          "cluster_id": 24,
          "warehouse_id": 2,
          "transport_type": "car",
          "order_ids": [
            71,
            95
          ]
        },
        {
          "cluster_id": 25,
          "warehouse_id": 3,
          "transport_type": "car",
          "order_ids": [
            108,
            101,
            120,
            135,
            143
          ]
        },
        {
          "cluster_id": 26,
          "warehouse_id": 3,
          "transport_type": "car",
          "order_ids": [
            102,
            114,
            137,
            147
          ]
        },
        {
          "cluster_id": 27,
          "warehouse_id": 3,
          "transport_type": "car",
          "order_ids": [
            115,
            103,
            141,
            118,
            112
          ]
        },
        {
          "cluster_id": 28,
          "warehouse_id": 3,
          "transport_type": "car",
          "order_ids": [
            104,
            121,
            132,
            127,
            139
          ]
        },
        {
          "cluster_id": 29,
          "warehouse_id": 3,
          "transport_type": "car",
          "order_ids": [
            106,
            109,
            105,
            128,
            149
          ]
        },
        {
          "cluster_id": 30,
          "warehouse_id": 3,
          "transport_type": "car",
          "order_ids": [
            116,
            123,
            107,
            140,
            124
          ]
        },
        {
          "cluster_id": 31,
          "warehouse_id": 3,
          "transport_type": "car",
          "order_ids": [
            110,
            125,
            117,
            131,
            122
          ]
        },
        {
          "cluster_id": 32,
          "warehouse_id": 3,
          "transport_type": "car",
          "order_ids": [
            111,
            119,
            130,
            145,
            129
          ]
        },
        {
          "cluster_id": 33,
          "warehouse_id": 3,
          "transport_type": "car",
          "order_ids": [
            148,
            113,
            138,
            142,
            150
          ]
        },
        {
          "cluster_id": 34,
          "warehouse_id": 3,
          "transport_type": "car",
          "order_ids": [
            126,
            133,
            134,
            144
          ]
        },
        {
          "cluster_id": 35,
          "warehouse_id": 3,
          "transport_type": "car",
          "order_ids": [
            136,
            146
          ]
        },
        {
          "cluster_id": 36,
          "warehouse_id": 4,
          "transport_type": "car",
          "order_ids": [
            151,
            159,
            153,
            160
          ]
        },
        {
          "cluster_id": 37,
          "warehouse_id": 4,
          "transport_type": "car",
          "order_ids": [
            172,
            152,
            196,
            176,
            199
          ]
        },
        {
          "cluster_id": 38,
          "warehouse_id": 4,
          "transport_type": "car",
          "order_ids": [
            161,
            154,
            191,
            157
          ]
        },
        {
          "cluster_id": 39,
          "warehouse_id": 4,
          "transport_type": "car",
          "order_ids": [
            155,
            174,
            197,
            181,
            193
          ]
        },
        {
          "cluster_id": 40,
          "warehouse_id": 4,
          "transport_type": "car",
          "order_ids": [
            180,
            156,
            179,
            186,
            195
          ]
        },
        {
          "cluster_id": 41,
          "warehouse_id": 4,
          "transport_type": "car",
          "order_ids": [
            158,
            188
          ]
        },
        {
          "cluster_id": 42,
          "warehouse_id": 4,
          "transport_type": "car",
          "order_ids": [
            162,
            170,
            187,
            200
          ]
        },
        {
          "cluster_id": 43,
          "warehouse_id": 4,
          "transport_type": "car",
          "order_ids": [
            166,
            163,
            178,
            183,
            198
          ]
        },
        {
          "cluster_id": 44,
          "warehouse_id": 4,
          "transport_type": "car",
          "order_ids": [
            164,
            167,
            182,
            171,
            190
          ]
        },
        {
          "cluster_id": 45,
          "warehouse_id": 4,
          "transport_type": "car",
          "order_ids": [
            165,
            168,
            177,
            194,
            192
          ]
        },
        {
          "cluster_id": 46,
          "warehouse_id": 4,
          "transport_type": "car",
          "order_ids": [
            185,
            169,
            173,
            189,
            175
          ]
        },
        {
          "cluster_id": 47,
          "warehouse_id": 4,
          "transport_type": "car",
          "order_ids": [
            184
          ]
        }
      ]
    }
  ],
  "task_7": [
    {
      "clusterization_id": 1,
      "fitness_score": 1472.376432290845,
      "is_valid": false,
      "clusters": [
        {
          "cluster_id": 1,
          "warehouse_id": 1,
          "transport_type": "car",
          "order_ids": [
            21,
            3,
            28,
            1,
            24
          ]
        },
        {
          "cluster_id": 2,
          "warehouse_id": 1,
          "transport_type": "car",
          "order_ids": [
            15,
            2,
            22
          ]
        },
        {
          "cluster_id": 3,
          "warehouse_id": 1,
          "transport_type": "car",
          "order_ids": [
            10,
            4,
            47,
            41,
            45
          ]
        },
        {
          "cluster_id": 4,
          "warehouse_id": 1,
          "transport_type": "car",
          "order_ids": [
            18,
            40,
            5,
            19,
            48
          ]
        },
        {
          "cluster_id": 5,
          "warehouse_id": 1,
          "transport_type": "car",
          "order_ids": [
            17,
            14,
            25,
            6,
            33
          ]
        },
        {
          "cluster_id": 6,
          "warehouse_id": 1,
          "transport_type": "car",
          "order_ids": [
            23,
            7,
            30,
            20,
            26
          ]
        },
        {
          "cluster_id": 7,
          "warehouse_id": 1,
          "transport_type": "car",
          "order_ids": [
            8,
            46
          ]
        },
        {
          "cluster_id": 8,
          "warehouse_id": 1,
          "transport_type": "car",
          "order_ids": [
            34,
            29,
            9,
            32,
            49
          ]
        },
        {
          "cluster_id": 9,
          "warehouse_id": 1,
          "transport_type": "car",
          "order_ids": [
            11,
            13
          ]
        },
        {
          "cluster_id": 10,
          "warehouse_id": 1,
          "transport_type": "car",
          "order_ids": [
            35,
            12,
            44,
            36,
            27
          ]
        },
        {
          "cluster_id": 11,
          "warehouse_id": 1,
          "transport_type": "car",
          "order_ids": [
            16,
            43
          ]
        },
        {
          "cluster_id": 12,
          "warehouse_id": 1,
          "transport_type": "car",
          "order_ids": [
            31,
            37,
            39,
            42
          ]
        },
        {
          "cluster_id": 13,
          "warehouse_id": 1,
          "transport_type": "car",
          "order_ids": [
            38,
            50
          ]
        },
        {
          "cluster_id": 14,
          "warehouse_id": 2,
          "transport_type": "car",
          "order_ids": [
            70,
            51,
            68,
            80,
            72
          ]
        },
        {
          "cluster_id": 15,
          "warehouse_id": 2,
          "transport_type": "car",
          "order_ids": [
            52,
            78,
            91,
            93
          ]
        },
        {
          "cluster_id": 16,
          "warehouse_id": 2,
          "transport_type": "car",
          "order_ids": [
            85,
            53,
            86,
            77,
            95
          ]
        },
        {
          "cluster_id": 17,
          "warehouse_id": 2,
          "transport_type": "car",
          "order_ids": [
            54,
            59,
            66,
            83,
            76
          ]
        },
        {
          "cluster_id": 18,
          "warehouse_id": 2,
          "transport_type": "car",
          "order_ids": [
            67,
            94,
            55,
            90,
            92
          ]
        },
        {
          "cluster_id": 19,
          "warehouse_id": 2,
          "transport_type": "car",
          "order_ids": [
            56,
            57,
            62
          ]
        },
        {
          "cluster_id": 20,
          "warehouse_id": 2,
          "transport_type": "car",
          "order_ids": [
            58,
            65,
            64,
            82,
            99
          ]
        },
        {
          "cluster_id": 21,
          "warehouse_id": 2,
          "transport_type": "car",
          "order_ids": [
            60,
            61,
            74
          ]
        },
        {
          "cluster_id": 22,
          "warehouse_id": 2,
          "transport_type": "car",
          "order_ids": [
            63
          ]
        },
        {
          "cluster_id": 23,
          "warehouse_id": 2,
          "transport_type": "car",
          "order_ids": [
            75,
            69,
            84,
            96,
            97
          ]
        },
        {
          "cluster_id": 24,
          "warehouse_id": 2,
          "transport_type": "car",
          "order_ids": [
            71,
            73,
            87,
            89
          ]
        },
        {
          "cluster_id": 25,
          "warehouse_id": 2,
          "transport_type": "car",
          "order_ids": [
            79,
            88,
            98,
            100
          ]
        },
        {
          "cluster_id": 26,
          "warehouse_id": 2,
          "transport_type": "car",
          "order_ids": [
            81
          ]
        },
        {
          "cluster_id": 27,
          "warehouse_id": 3,
          "transport_type": "car",
          "order_ids": [
            101,
            129,
            133
          ]
        },
        {
          "cluster_id": 28,
          "warehouse_id": 3,
          "transport_type": "car",
          "order_ids": [
            105,
            114,
            102,
            137,
            124
          ]
        },
        {
          "cluster_id": 29,
          "warehouse_id": 3,
          "transport_type": "car",
          "order_ids": [
            142,
            103,
            143,
            127,
            118
          ]
        },
        {
          "cluster_id": 30,
          "warehouse_id": 3,
          "transport_type": "car",
          "order_ids": [
            147,
            104,
            109,
            149,
            130
          ]
        },
        {
          "cluster_id": 31,
          "warehouse_id": 3,
          "transport_type": "car",
          "order_ids": [
            106,
            122,
            117,
            121,
            135
          ]
        },
        {
          "cluster_id": 32,
          "warehouse_id": 3,
          "transport_type": "car",
          "order_ids": [
            112,
            126,
            107,
            139,
            140
          ]
        },
        {
          "cluster_id": 33,
          "warehouse_id": 3,
          "transport_type": "car",
          "order_ids": [
            115,
            108,
            125,
            145,
            110
          ]
        },
        {
          "cluster_id": 34,
          "warehouse_id": 3,
          "transport_type": "car",
          "order_ids": [
            111,
            119,
            123,
            132
          ]
        },
        {
          "cluster_id": 35,
          "warehouse_id": 3,
          "transport_type": "car",
          "order_ids": [
            113,
            120,
            116,
            136
          ]
        },
        {
          "cluster_id": 36,
          "warehouse_id": 3,
          "transport_type": "car",
          "order_ids": [
            128,
            150
          ]
        },
        {
          "cluster_id": 37,
          "warehouse_id": 3,
          "transport_type": "car",
          "order_ids": [
            138,
            131,
            134,
            148
          ]
        },
        {
          "cluster_id": 38,
          "warehouse_id": 3,
          "transport_type": "car",
          "order_ids": [
            141,
            146,
            144
          ]
        },
        {
          "cluster_id": 39,
          "warehouse_id": 4,
          "transport_type": "car",
          "order_ids": [
            151,
            153,
            161,
            192,
            200
          ]
        },
        {
          "cluster_id": 40,
          "warehouse_id": 4,
          "transport_type": "car",
          "order_ids": [
            182,
            152,
            181,
            189,
            155
          ]
        },
        {
          "cluster_id": 41,
          "warehouse_id": 4,
          "transport_type": "car",
          "order_ids": [
            154,
            173,
            190,
            180,
            198
          ]
        },
        {
          "cluster_id": 42,
          "warehouse_id": 4,
          "transport_type": "car",
          "order_ids": [
            172,
            156,
            170,
            178,
            186
          ]
        },
        {
          "cluster_id": 43,
          "warehouse_id": 4,
          "transport_type": "car",
          "order_ids": [
            157,
            166,
            191
          ]
        },
        {
          "cluster_id": 44,
          "warehouse_id": 4,
          "transport_type": "car",
          "order_ids": [
            171,
            175,
            158,
            177,
            187
          ]
        },
        {
          "cluster_id": 45,
          "warehouse_id": 4,
          "transport_type": "car",
          "order_ids": [
            167,
            194,
            159,
            185,
            196
          ]
        },
        {
          "cluster_id": 46,
          "warehouse_id": 4,
          "transport_type": "car",
          "order_ids": [
            160,
            163,
            183,
            184,
            199
          ]
        },
        {
          "cluster_id": 47,
          "warehouse_id": 4,
          "transport_type": "car",
          "order_ids": [
            162,
            193,
            195
          ]
        },
        {
          "cluster_id": 48,
          "warehouse_id": 4,
          "transport_type": "car",
          "order_ids": [
            169,
            164,
            168,
            174,
            179
          ]
        },
        {
          "cluster_id": 49,
          "warehouse_id": 4,
          "transport_type": "car",
          "order_ids": [
            176,
            165,
            197,
            188
          ]
        },
        {
          "cluster_id": 50,
          "warehouse_id": 5,
          "transport_type": "car",
          "order_ids": [
            213,
            201,
            221,
            222
          ]
        },
        {
          "cluster_id": 51,
          "warehouse_id": 5,
          "transport_type": "car",
          "order_ids": [
            207,
            202,
            227,
            228,
            250
          ]
        },
        {
          "cluster_id": 52,
          "warehouse_id": 5,
          "transport_type": "car",
          "order_ids": [
            230,
            234,
            208,
            203,
            242
          ]
        },
        {
          "cluster_id": 53,
          "warehouse_id": 5,
          "transport_type": "car",
          "order_ids": [
            204,
            223,
            229,
            236,
            247
          ]
        },
        {
          "cluster_id": 54,
          "warehouse_id": 5,
          "transport_type": "car",
          "order_ids": [
            205,
            244,
            246,
            237
          ]
        },
        {
          "cluster_id": 55,
          "warehouse_id": 5,
          "transport_type": "car",
          "order_ids": [
            206,
            218,
            241,
            240,
            238
          ]
        },
        {
          "cluster_id": 56,
          "warehouse_id": 5,
          "transport_type": "car",
          "order_ids": [
            209,
            217
          ]
        },
        {
          "cluster_id": 57,
          "warehouse_id": 5,
          "transport_type": "car",
          "order_ids": [
            210,
            243,
            249,
            233,
            232
          ]
        },
        {
          "cluster_id": 58,
          "warehouse_id": 5,
          "transport_type": "car",
          "order_ids": [
            211,
            219,
            225,
            216,
            235
          ]
        },
        {
          "cluster_id": 59,
          "warehouse_id": 5,
          "transport_type": "car",
          "order_ids": [
            215,
            212,
            220,
            224,
            245
          ]
        },
        {
          "cluster_id": 60,
          "warehouse_id": 5,
          "transport_type": "car",
          "order_ids": [
            226,
            231,
            214,
            239,
            248
          ]
        }
      ]
    }
  ],
  "task_8": [
    {
      "clusterization_id": 1,
      "fitness_score": 115.69983356237508,
      "is_valid": true,
      "clusters": [
        {
          "cluster_id": 1,
          "warehouse_id": 1,
          "transport_type": "car",
          "order_ids": [
            1,
            33,
            18,
            32,
            44
          ]
        },
        {
          "cluster_id": 2,
          "warehouse_id": 1,
          "transport_type": "car",
          "order_ids": [
            2,
            8,
            12,
            17,
            21
          ]
        },
        {
          "cluster_id": 3,
          "warehouse_id": 1,
          "transport_type": "car",
          "order_ids": [
            6,
            3,
            23,
            22,
            43
          ]
        },
        {
          "cluster_id": 4,
          "warehouse_id": 1,
          "transport_type": "car",
          "order_ids": [
            24,
            4,
            15,
            28,
            27
          ]
        },
        {
          "cluster_id": 5,
          "warehouse_id": 1,
          "transport_type": "car",
          "order_ids": [
            5,
            7,
            45,
            50
          ]
        },
        {
          "cluster_id": 6,
          "warehouse_id": 1,
          "transport_type": "car",
          "order_ids": [
            9,
            26
          ]
        },
        {
          "cluster_id": 7,
          "warehouse_id": 1,
          "transport_type": "car",
          "order_ids": [
            10,
            13,
            42,
            38,
            46
          ]
        },
        {
          "cluster_id": 8,
          "warehouse_id": 1,
          "transport_type": "car",
          "order_ids": [
            11,
            41
          ]
        },
        {
          "cluster_id": 9,
          "warehouse_id": 1,
          "transport_type": "car",
          "order_ids": [
            36,
            14,
            40,
            47
          ]
        },
        {
          "cluster_id": 10,
          "warehouse_id": 1,
          "transport_type": "car",
          "order_ids": [
            16,
            19,
            39
          ]
        },
        {
          "cluster_id": 11,
          "warehouse_id": 1,
          "transport_type": "car",
          "order_ids": [
            20,
            25,
            34,
            37,
            31
          ]
        },
        {
          "cluster_id": 12,
          "warehouse_id": 1,
          "transport_type": "car",
          "order_ids": [
            29,
            49,
            35,
            48,
            30
          ]
        },
        {
          "cluster_id": 13,
          "warehouse_id": 2,
          "transport_type": "car",
          "order_ids": [
            78,
            56,
            51,
            89,
            98
          ]
        },
        {
          "cluster_id": 14,
          "warehouse_id": 2,
          "transport_type": "car",
          "order_ids": [
            57,
            52,
            83,
            97,
            84
          ]
        },
        {
          "cluster_id": 15,
          "warehouse_id": 2,
          "transport_type": "car",
          "order_ids": [
            69,
            53,
            58,
            96,
            66
          ]
        },
        {
          "cluster_id": 16,
          "warehouse_id": 2,
          "transport_type": "car",
          "order_ids": [
            54,
            75,
            87,
            81,
            88
          ]
        },
        {
          "cluster_id": 17,
          "warehouse_id": 2,
          "transport_type": "car",
          "order_ids": [
            55,
            85
          ]
        },
        {
          "cluster_id": 18,
          "warehouse_id": 2,
          "transport_type": "car",
          "order_ids": [
            77,
            90,
            59,
            99,
            65
          ]
        },
        {
          "cluster_id": 19,
          "warehouse_id": 2,
          "transport_type": "car",
          "order_ids": [
            60,
            94,
            82
          ]
        },
        {
          "cluster_id": 20,
          "warehouse_id": 2,
          "transport_type": "car",
          "order_ids": [
            74,
            63,
            61,
            100,
            80
          ]
        },
        {
          "cluster_id": 21,
          "warehouse_id": 2,
          "transport_type": "car",
          "order_ids": [
            62,
            64,
            76,
            79,
            92
          ]
        },
        {
          "cluster_id": 22,
          "warehouse_id": 2,
          "transport_type": "car",
          "order_ids": [
            67,
            73,
            70,
            86,
            91
          ]
        },
        {
          "cluster_id": 23,
          "warehouse_id": 2,
          "transport_type": "car",
          "order_ids": [
            68,
            71,
            72,
            93,
            95
          ]
        }
      ]
    }
  ],
  "task_9": [
    {
      "clusterization_id": 1,
      "fitness_score": 1118.4771036826442,
      "is_valid": false,
      "clusters": [
        {
          "cluster_id": 1,
          "warehouse_id": 1,
          "transport_type": "car",
          "order_ids": [
            13,
            1,
            6,
            38,
            24
          ]
        },
        {
          "cluster_id": 2,
          "warehouse_id": 1,
          "transport_type": "car",
          "order_ids": [
            35,
            41,
            2,
            26,
            43
          ]
        },
        {
          "cluster_id": 3,
          "warehouse_id": 1,
          "transport_type": "car",
          "order_ids": [
            28,
            40,
            3,
            15,
            50
          ]
        },
        {
          "cluster_id": 4,
          "warehouse_id": 1,
          "transport_type": "car",
          "order_ids": [
            4,
            10,
            21,
            45,
            30
          ]
        },
        {
          "cluster_id": 5,
          "warehouse_id": 1,
          "transport_type": "car",
          "order_ids": [
            5,
            17,
            12,
            25,
            27
          ]
        },
        {
          "cluster_id": 6,
          "warehouse_id": 1,
          "transport_type": "car",
          "order_ids": [
            7,
            8,
            18,
            29,
            46
          ]
        },
        {
          "cluster_id": 7,
          "warehouse_id": 1,
          "transport_type": "car",
          "order_ids": [
            9,
            44,
            23
          ]
        },
        {
          "cluster_id": 8,
          "warehouse_id": 1,
          "transport_type": "car",
          "order_ids": [
            11,
            19,
            37,
            42,
            47
          ]
        },
        {
          "cluster_id": 9,
          "warehouse_id": 1,
          "transport_type": "car",
          "order_ids": [
            14,
            33,
            31,
            39,
            36
          ]
        },
        {
          "cluster_id": 10,
          "warehouse_id": 1,
          "transport_type": "car",
          "order_ids": [
            16,
            32,
            34,
            48,
            49
          ]
        },
        {
          "cluster_id": 11,
          "warehouse_id": 1,
          "transport_type": "car",
          "order_ids": [
            20,
            22
          ]
        },
        {
          "cluster_id": 12,
          "warehouse_id": 2,
          "transport_type": "car",
          "order_ids": [
            55,
            51,
            100,
            90,
            80
          ]
        },
        {
          "cluster_id": 13,
          "warehouse_id": 2,
          "transport_type": "car",
          "order_ids": [
            52,
            53,
            67,
            77,
            85
          ]
        },
        {
          "cluster_id": 14,
          "warehouse_id": 2,
          "transport_type": "car",
          "order_ids": [
            59,
            54,
            70,
            65,
            95
          ]
        },
        {
          "cluster_id": 15,
          "warehouse_id": 2,
          "transport_type": "car",
          "order_ids": [
            60,
            83,
            56,
            73,
            89
          ]
        },
        {
          "cluster_id": 16,
          "warehouse_id": 2,
          "transport_type": "car",
          "order_ids": [
            57,
            76
          ]
        },
        {
          "cluster_id": 17,
          "warehouse_id": 2,
          "transport_type": "car",
          "order_ids": [
            64,
            58,
            74,
            98,
            82
          ]
        },
        {
          "cluster_id": 18,
          "warehouse_id": 2,
          "transport_type": "car",
          "order_ids": [
            94,
            61,
            86,
            99
          ]
        },
        {
          "cluster_id": 19,
          "warehouse_id": 2,
          "transport_type": "car",
          "order_ids": [
            62,
            87,
            66,
            96,
            97
          ]
        },
        {
          "cluster_id": 20,
          "warehouse_id": 2,
          "transport_type": "car",
          "order_ids": [
            63,
            75,
            84,
            93,
            78
          ]
        },
        {
          "cluster_id": 21,
          "warehouse_id": 2,
          "transport_type": "car",
          "order_ids": [
            79,
            68,
            81,
            88
          ]
        },
        {
          "cluster_id": 22,
          "warehouse_id": 2,
          "transport_type": "car",
          "order_ids": [
            71,
            69,
            72,
            91,
            92
          ]
        },
        {
          "cluster_id": 23,
          "warehouse_id": 3,
          "transport_type": "car",
          "order_ids": [
            101,
            115,
            122,
            132,
            116
          ]
        },
        {
          "cluster_id": 24,
          "warehouse_id": 3,
          "transport_type": "car",
          "order_ids": [
            114,
            119,
            102,
            129,
            118
          ]
        },
        {
          "cluster_id": 25,
          "warehouse_id": 3,
          "transport_type": "car",
          "order_ids": [
            103,
            126,
            146,
            110
          ]
        },
        {
          "cluster_id": 26,
          "warehouse_id": 3,
          "transport_type": "car",
          "order_ids": [
            104,
            130,
            141,
            142
          ]
        },
        {
          "cluster_id": 27,
          "warehouse_id": 3,
          "transport_type": "car",
          "order_ids": [
            105,
            112,
            123
          ]
        },
        {
          "cluster_id": 28,
          "warehouse_id": 3,
          "transport_type": "car",
          "order_ids": [
            106,
            135,
            121,
            117
          ]
        },
        {
          "cluster_id": 29,
          "warehouse_id": 3,
          "transport_type": "car",
          "order_ids": [
            107,
            138,
            147,
            144
          ]
        },
        {
          "cluster_id": 30,
          "warehouse_id": 3,
          "transport_type": "car",
          "order_ids": [
            108,
            111,
            131,
            148,
            149
          ]
        },
        {
          "cluster_id": 31,
          "warehouse_id": 3,
          "transport_type": "car",
          "order_ids": [
            109,
            134,
            133,
            145,
            136
          ]
        },
        {
          "cluster_id": 32,
          "warehouse_id": 3,
          "transport_type": "car",
          "order_ids": [
            113,
            125,
            150
          ]
        },
        {
          "cluster_id": 33,
          "warehouse_id": 3,
          "transport_type": "car",
          "order_ids": [
            120,
            128,
            127,
            124,
            139
          ]
        },
        {
          "cluster_id": 34,
          "warehouse_id": 3,
          "transport_type": "car",
          "order_ids": [
            137,
            140
          ]
        },
        {
          "cluster_id": 35,
          "warehouse_id": 3,
          "transport_type": "car",
          "order_ids": [
            143
          ]
        },
        {
          "cluster_id": 36,
          "warehouse_id": 4,
          "transport_type": "car",
          "order_ids": [
            184,
            151,
            192,
            158,
            164
          ]
        },
        {
          "cluster_id": 37,
          "warehouse_id": 4,
          "transport_type": "car",
          "order_ids": [
            152,
            162,
            178,
            190,
            163
          ]
        },
        {
          "cluster_id": 38,
          "warehouse_id": 4,
          "transport_type": "car",
          "order_ids": [
            171,
            186,
            153,
            196
          ]
        },
        {
          "cluster_id": 39,
          "warehouse_id": 4,
          "transport_type": "car",
          "order_ids": [
            160,
            154,
            182,
            194
          ]
        },
        {
          "cluster_id": 40,
          "warehouse_id": 4,
          "transport_type": "car",
          "order_ids": [
            155,
            180,
            187,
            188,
            179
          ]
        },
        {
          "cluster_id": 41,
          "warehouse_id": 4,
          "transport_type": "car",
          "order_ids": [
            156,
            166,
            175,
            177,
            185
          ]
        },
        {
          "cluster_id": 42,
          "warehouse_id": 4,
          "transport_type": "car",
          "order_ids": [
            165,
            157,
            168,
            167,
            169
          ]
        },
        {
          "cluster_id": 43,
          "warehouse_id": 4,
          "transport_type": "car",
          "order_ids": [
            159,
            173
          ]
        },
        {
          "cluster_id": 44,
          "warehouse_id": 4,
          "transport_type": "car",
          "order_ids": [
            170,
            174,
            195,
            161,
            197
          ]
        },
        {
          "cluster_id": 45,
          "warehouse_id": 4,
          "transport_type": "car",
          "order_ids": [
            172,
            191,
            189,
            199
          ]
        },
        {
          "cluster_id": 46,
          "warehouse_id": 4,
          "transport_type": "car",
          "order_ids": [
            176
          ]
        },
        {
          "cluster_id": 47,
          "warehouse_id": 4,
          "transport_type": "car",
          "order_ids": [
            181,
            193,
            198
          ]
        },
        {
          "cluster_id": 48,
          "warehouse_id": 4,
          "transport_type": "car",
          "order_ids": [
            183,
            200
          ]
        }
      ]
    }
  ],
  "task_10": [
    {
      "clusterization_id": 1,
      "fitness_score": 2550.0577703887648,
      "is_valid": false,
      "clusters": [
        {
          "cluster_id": 1,
          "warehouse_id": 1,
          "transport_type": "car",
          "order_ids": [
            1,
            48,
            16,
            50
          ]
        },
        {
          "cluster_id": 2,
          "warehouse_id": 1,
          "transport_type": "car",
          "order_ids": [
            9,
            2,
            45,
            23,
            24
          ]
        },
        {
          "cluster_id": 3,
          "warehouse_id": 1,
          "transport_type": "car",
          "order_ids": [
            3,
            15,
            33,
            36
          ]
        },
        {
          "cluster_id": 4,
          "warehouse_id": 1,
          "transport_type": "car",
          "order_ids": [
            4,
            14,
            26,
            37,
            41
          ]
        },
        {
          "cluster_id": 5,
          "warehouse_id": 1,
          "transport_type": "car",
          "order_ids": [
            6,
            5,
            29,
            32,
            44
          ]
        },
        {
          "cluster_id": 6,
          "warehouse_id": 1,
          "transport_type": "car",
          "order_ids": [
            7,
            31
          ]
        },
        {
          "cluster_id": 7,
          "warehouse_id": 1,
          "transport_type": "car",
          "order_ids": [
            8,
            18,
            13,
            25,
            28
          ]
        },
        {
          "cluster_id": 8,
          "warehouse_id": 1,
          "transport_type": "car",
          "order_ids": [
            10,
            38,
            40,
            49,
            47
          ]
        },
        {
          "cluster_id": 9,
          "warehouse_id": 1,
          "transport_type": "car",
          "order_ids": [
            11
          ]
        },
        {
          "cluster_id": 10,
          "warehouse_id": 1,
          "transport_type": "car",
          "order_ids": [
            12,
            17,
            21,
            35,
            43
          ]
        },
        {
          "cluster_id": 11,
          "warehouse_id": 1,
          "transport_type": "car",
          "order_ids": [
            19,
            20,
            27,
            39,
            30
          ]
        },
        {
          "cluster_id": 12,
          "warehouse_id": 1,
          "transport_type": "car",
          "order_ids": [
            22,
            34
          ]
        },
        {
          "cluster_id": 13,
          "warehouse_id": 1,
          "transport_type": "car",
          "order_ids": [
            42,
            46
          ]
        },
        {
          "cluster_id": 14,
          "warehouse_id": 2,
          "transport_type": "car",
          "order_ids": [
            51,
            95,
            79
          ]
        },
        {
          "cluster_id": 15,
          "warehouse_id": 2,
          "transport_type": "car",
          "order_ids": [
            52,
            68
          ]
        },
        {
          "cluster_id": 16,
          "warehouse_id": 2,
          "transport_type": "car",
          "order_ids": [
            53,
            62,
            74
          ]
        },
        {
          "cluster_id": 17,
          "warehouse_id": 2,
          "transport_type": "car",
          "order_ids": [
            55,
            59,
            54,
            84,
            66
          ]
        },
        {
          "cluster_id": 18,
          "warehouse_id": 2,
          "transport_type": "car",
          "order_ids": [
            56,
            77,
            58,
            73,
            80
          ]
        },
        {
          "cluster_id": 19,
          "warehouse_id": 2,
          "transport_type": "car",
          "order_ids": [
            57
          ]
        },
        {
          "cluster_id": 20,
          "warehouse_id": 2,
          "transport_type": "car",
          "order_ids": [
            60,
            70,
            81,
            88,
            93
          ]
        },
        {
          "cluster_id": 21,
          "warehouse_id": 2,
          "transport_type": "car",
          "order_ids": [
            61,
            99
          ]
        },
        {
          "cluster_id": 22,
          "warehouse_id": 2,
          "transport_type": "car",
          "order_ids": [
            89,
            63,
            67,
            75,
            96
          ]
        },
        {
          "cluster_id": 23,
          "warehouse_id": 2,
          "transport_type": "car",
          "order_ids": [
            71,
            78,
            76,
            64,
            92
          ]
        },
        {
          "cluster_id": 24,
          "warehouse_id": 2,
          "transport_type": "car",
          "order_ids": [
            65,
            69,
            86,
            100,
            91
          ]
        },
        {
          "cluster_id": 25,
          "warehouse_id": 2,
          "transport_type": "car",
          "order_ids": [
            72,
            90
          ]
        },
        {
          "cluster_id": 26,
          "warehouse_id": 2,
          "transport_type": "car",
          "order_ids": [
            82,
            94,
            83,
            85,
            87
          ]
        },
        {
          "cluster_id": 27,
          "warehouse_id": 2,
          "transport_type": "car",
          "order_ids": [
            97,
            98
          ]
        },
        {
          "cluster_id": 28,
          "warehouse_id": 3,
          "transport_type": "car",
          "order_ids": [
            101,
            109,
            140,
            149,
            133
          ]
        },
        {
          "cluster_id": 29,
          "warehouse_id": 3,
          "transport_type": "car",
          "order_ids": [
            107,
            114,
            102,
            110,
            146
          ]
        },
        {
          "cluster_id": 30,
          "warehouse_id": 3,
          "transport_type": "car",
          "order_ids": [
            103,
            105,
            135,
            118,
            117
          ]
        },
        {
          "cluster_id": 31,
          "warehouse_id": 3,
          "transport_type": "car",
          "order_ids": [
            116,
            104,
            126,
            129,
            132
          ]
        },
        {
          "cluster_id": 32,
          "warehouse_id": 3,
          "transport_type": "car",
          "order_ids": [
            106,
            137,
            121,
            147
          ]
        },
        {
          "cluster_id": 33,
          "warehouse_id": 3,
          "transport_type": "car",
          "order_ids": [
            108,
            113,
            131,
            143,
            138
          ]
        },
        {
          "cluster_id": 34,
          "warehouse_id": 3,
          "transport_type": "car",
          "order_ids": [
            111,
            122,
            136,
            145,
            148
          ]
        },
        {
          "cluster_id": 35,
          "warehouse_id": 3,
          "transport_type": "car",
          "order_ids": [
            134,
            112,
            142,
            127,
            139
          ]
        },
        {
          "cluster_id": 36,
          "warehouse_id": 3,
          "transport_type": "car",
          "order_ids": [
            119,
            123,
            115,
            144,
            125
          ]
        },
        {
          "cluster_id": 37,
          "warehouse_id": 3,
          "transport_type": "car",
          "order_ids": [
            124,
            120,
            128,
            141,
            150
          ]
        },
        {
          "cluster_id": 38,
          "warehouse_id": 3,
          "transport_type": "car",
          "order_ids": [
            130
          ]
        }
      ]
    }
  ]
}